resmap/__init__.py
resmap/bibtex.py
resmap/constants.py
resmap/protocols.conf
resmap/resmap_logo.png
resmap/wizards.py
resmap/protocols/__init__.py
resmap/protocols/protocol_resmap.py
resmap/tests/__init__.py
resmap/tests/test_protocols_resmap.py
resmap/viewers/__init__.py
resmap/viewers/resmap_viewers.py
scipion_em_resmap-3.0.3.dist-info/LICENSE
scipion_em_resmap-3.0.3.dist-info/METADATA
scipion_em_resmap-3.0.3.dist-info/WHEEL
scipion_em_resmap-3.0.3.dist-info/entry_points.txt
scipion_em_resmap-3.0.3.dist-info/top_level.txt
scipion_em_resmap-3.0.3.dist-info/RECORD
