Metadata-Version: 2.1
Name: scipion-em-resmap
Version: 3.0.3
Summary: Plugin to use ResMap program within the Scipion framework
Home-page: https://github.com/scipion-em/scipion-em-resmap
Author: I2PC
Author-email: scipion@cnb.csic.es
License: UNKNOWN
Keywords: scipion electron-microscopy cryo-em structural-biology image-processing scipion-3.0
Platform: UNKNOWN
Classifier: Development Status :: 4 - Beta
Classifier: License :: OSI Approved :: GNU General Public License v3 (GPLv3)
Classifier: Programming Language :: Python :: 3
